{
  "culture": "hr",
  "texts": {
    "Languages": "Jezici",
    "AreYouSure": "Jeste li sigurni?",
    "Cancel": "Odustani",
    "Clear": "Očisti",
    "Yes": "Da",
    "No": "Ne",
    "Ok": "Ok",
    "Close": "Zatvori",
    "Save": "Snimi",
    "SavingWithThreeDot": "Snimanje...",
    "Actions": "Akcije",
    "Delete": "Obriši",
    "Edit": "Uredi",
    "Refresh": "Osvježi",
    "Language": "Jezik",
    "LoadMore": "Učitaj više",
    "ProcessingWithThreeDot": "Obrađujem...",
    "LoadingWithThreeDot": "Učitavanje...",
    "Welcome": "Dobrodošli",
    "Login": "Prijava",
    "Register": "Registracija",
    "Logout": "Odjava",
    "Submit": "Podnesi",
    "Back": "Natrag",
    "PagerSearch": "Pretraži",
    "PagerNext": "Sljedeća",
    "PagerPrevious": "Prethodna",
    "PagerFirst": "Prva",
    "PagerLast": "Zadnja",
    "PagerInfo": "Prikazuje se _START_ do _END_ od _TOTAL_ unosa",
    "PagerInfo{0}{1}{2}": "Prikauje se {0} do {1} od {2} unosa",
    "PagerInfoEmpty": "Prikazuje se 0 do 0 od 0 unosa",
    "PagerInfoFiltered": "(filtrirano od _MAX_ ukupnog broja unosa)",
    "NoDataAvailableInDatatable": "Nema dostupnih podataka",
    "Total": "ukupno",
    "Selected": "odabrano",
    "PagerShowMenuEntries": "Prikaži _MENU_ unose",
    "DatatableActionDropdownDefaultText": "Akcije",
    "ChangePassword": "Promijeni lozinku",
    "PersonalInfo": "Moj profil",
    "AreYouSureYouWantToCancelEditingWarningMessage": "Imate nespremljene promjene.",
    "GoHomePage": "Idi na početnu stranicu",
    "GoBack": "Idi nazad",
    "Search": "Pretraži",
    "ItemWillBeDeletedMessageWithFormat": "{0} će biti obrisan!",
    "ItemWillBeDeletedMessage": "Ova stavka će biti obrisana!",
    "ManageYourAccount": "Uredi svoj račun"
  }
}
